[{"name":"","score":"0","date":"Wednesday, April 02, 2014","time":"04:19:06"},{"name":"Matt","score":"8250","date":"Wednesday, April 02, 2014","time":"04:20:27"},{"name":"Matt","score":"36900","date":"Wednesday, April 02, 2014","time":"04:22:21"},{"name":"","score":"13600","date":"Wednesday, April 02, 2014","time":"04:42:24"},{"name":"John","score":"57400","date":"Wednesday, April 02, 2014","time":"08:40:09"},{"name":"John","score":"35250","date":"Wednesday, April 02, 2014","time":"12:22:42"},{"name":"John","score":"85600","date":"Wednesday, April 02, 2014","time":"12:27:09"},{"name":"John","score":"1350","date":"Wednesday, April 02, 2014","time":"12:51:36"},{"name":"test","score":"7950","date":"Wednesday, April 02, 2014","time":"12:52:10"},{"name":"Test","score":"19250","date":"Wednesday, April 02, 2014","time":"13:06:12"},{"name":"John","score":"4100","date":"Wednesday, April 02, 2014","time":"13:06:59"},{"name":"Matt","score":"59750","date":"Wednesday, April 02, 2014","time":"13:17:05"},{"name":"Matt","score":"6450","date":"Wednesday, April 02, 2014","time":"13:54:30"},{"name":"Matt","score":"6000","date":"Wednesday, April 02, 2014","time":"14:02:52"},{"name":"Matt","score":"0","date":"Wednesday, April 02, 2014","time":"14:23:22"},{"name":"","score":"0","date":"Wednesday, April 02, 2014","time":"14:47:29"}]